jsondb/__init__.py
jsondb/jsondb.py
jsondb2-0.0.3.dist-info/METADATA
jsondb2-0.0.3.dist-info/WHEEL
jsondb2-0.0.3.dist-info/top_level.txt
jsondb2-0.0.3.dist-info/RECORD
