Metadata-Version: 2.1
Name: jsondb2
Version: 0.0.3
Summary: Use json file as database
Home-page: https://github.com/sinofarmonovzfkrvjl/JsonDB
Classifier: Programming Language :: Python :: 3
